[
  { "code": "JP", "region": "Ази", "name": "Япон" },
  { "code": "KR", "region": "Ази", "name": "Солонгос" },
  { "code": "CN", "region": "Ази", "name": "Хятад" },
  { "code": "TW", "region": "Ази", "name": "Тайвань" },
  { "code": "HK", "region": "Ази", "name": "Хонг Конг" },
  { "code": "MO", "region": "Ази", "name": "Макао" },
  { "code": "SG", "region": "Ази", "name": "Сингапур" },
  { "code": "TH", "region": "Ази", "name": "Тайланд" },
  { "code": "MY", "region": "Ази", "name": "Малайз" },
  { "code": "VN", "region": "Ази", "name": "Вьетнам" },
  { "code": "ID", "region": "Ази", "name": "Индонез" },
  { "code": "PH", "region": "Ази", "name": "Филиппин" },
  { "code": "IN", "region": "Ази", "name": "Энэтхэг" },
  { "code": "BD", "region": "Ази", "name": "Бангладеш" },
  { "code": "LK", "region": "Ази", "name": "Шри Ланка" },
  { "code": "PK", "region": "Ази", "name": "Пакистан" },
  { "code": "NP", "region": "Ази", "name": "Балба" },
  { "code": "BT", "region": "Ази", "name": "Бутан" },
  { "code": "MM", "region": "Ази", "name": "Мьянмар" },
  { "code": "KH", "region": "Ази", "name": "Камбож" },
  { "code": "LA", "region": "Ази", "name": "Лаос" },
  { "code": "MV", "region": "Ази", "name": "Мальдив" },
  { "code": "AF", "region": "Ази", "name": "Афганистан" },
  { "code": "KZ", "region": "Төв Ази", "name": "Казахстан" },
  { "code": "UZ", "region": "Төв Ази", "name": "Узбекистан" },
  { "code": "KG", "region": "Төв Ази", "name": "Кыргызстан" },
  { "code": "TJ", "region": "Төв Ази", "name": "Тажикистан" },
  { "code": "TM", "region": "Төв Ази", "name": "Туркменистан" },
  { "code": "DE", "region": "Европ", "name": "Герман" },
  { "code": "GB", "region": "Европ", "name": "Их Британи" },
  { "code": "FR", "region": "Европ", "name": "Франц" },
  { "code": "IT", "region": "Европ", "name": "Итали" },
  { "code": "ES", "region": "Европ", "name": "Испани" },
  { "code": "PT", "region": "Европ", "name": "Португал" },
  { "code": "NL", "region": "Европ", "name": "Нидерланд" },
  { "code": "BE", "region": "Европ", "name": "Бельги" },
  { "code": "CH", "region": "Европ", "name": "Швейцар" },
  { "code": "AT", "region": "Европ", "name": "Австри" },
  { "code": "SE", "region": "Европ", "name": "Швед" },
  { "code": "NO", "region": "Европ", "name": "Норвеги" },
  { "code": "DK", "region": "Европ", "name": "Дани" },
  { "code": "FI", "region": "Европ", "name": "Финланд" },
  { "code": "IS", "region": "Европ", "name": "Исланд" },
  { "code": "IE", "region": "Европ", "name": "Ирланд" },
  { "code": "MT", "region": "Европ", "name": "Мальт" },
  { "code": "GR", "region": "Европ", "name": "Грек" },
  { "code": "TR", "region": "Европ", "name": "Турк" },
  { "code": "PL", "region": "Европ", "name": "Польш" },
  { "code": "CZ", "region": "Европ", "name": "Чех" },
  { "code": "SK", "region": "Европ", "name": "Словак" },
  { "code": "HU", "region": "Европ", "name": "Унгар" },
  { "code": "SI", "region": "Европ", "name": "Словени" },
  { "code": "HR", "region": "Европ", "name": "Хорват" },
  { "code": "BA", "region": "Европ", "name": "Босни Герцеговин" },
  { "code": "RS", "region": "Европ", "name": "Серби" },
  { "code": "BG", "region": "Европ", "name": "Болгар" },
  { "code": "RO", "region": "Европ", "name": "Румын" },
  { "code": "MD", "region": "Европ", "name": "Молдав" },
  { "code": "UA", "region": "Европ", "name": "Украйн" },
  { "code": "BY", "region": "Европ", "name": "Беларусь" },
  { "code": "RU", "region": "Европ", "name": "Орос" },
  { "code": "LT", "region": "Европ", "name": "Литва" },
  { "code": "LV", "region": "Европ", "name": "Латви" },
  { "code": "EE", "region": "Европ", "name": "Эстони" },
  { "code": "CY", "region": "Европ", "name": "Кипр" },
  { "code": "US", "region": "Хойд Америк", "name": "АНУ" },
  { "code": "CA", "region": "Хойд Америк", "name": "Канад" },
  { "code": "MX", "region": "Хойд Америк", "name": "Мексик" },
  { "code": "GT", "region": "Хойд Америк", "name": "Гватемал" },
  { "code": "BZ", "region": "Хойд Америк", "name": "Белиз" },
  { "code": "SV", "region": "Хойд Америк", "name": "Эль Сальвадор" },
  { "code": "HN", "region": "Хойд Америк", "name": "Гондурас" },
  { "code": "NI", "region": "Хойд Америк", "name": "Никарагуа" },
  { "code": "CR", "region": "Хойд Америк", "name": "Коста Рика" },
  { "code": "PA", "region": "Хойд Америк", "name": "Панам" },
  { "code": "CU", "region": "Хойд Америк", "name": "Куба" },
  { "code": "JM", "region": "Хойд Америк", "name": "Ямайка" },
  { "code": "HT", "region": "Хойд Америк", "name": "Гаити" },
  { "code": "DO", "region": "Хойд Америк", "name": "Бүгд Найрамдах Доминикан Улс" },
  { "code": "PR", "region": "Хойд Америк", "name": "Пуэрто Рико" },
  { "code": "BS", "region": "Хойд Америк", "name": "Багам" },
  { "code": "TT", "region": "Хойд Америк", "name": "Тринидад Тобаго" },
  { "code": "BB", "region": "Хойд Америк", "name": "Барбадос" },
  { "code": "BR", "region": "Өмнөд Америк", "name": "Бразил" },
  { "code": "AR", "region": "Өмнөд Америк", "name": "Аргентин" },
  { "code": "CL", "region": "Өмнөд Америк", "name": "Чили" },
  { "code": "PE", "region": "Өмнөд Америк", "name": "Перу" },
  { "code": "CO", "region": "Өмнөд Америк", "name": "Колумби" },
  { "code": "VE", "region": "Өмнөд Америк", "name": "Венесуэл" },
  { "code": "EC", "region": "Өмнөд Америк", "name": "Эквадор" },
  { "code": "UY", "region": "Өмнөд Америк", "name": "Уругвай" },
  { "code": "PY", "region": "Өмнөд Америк", "name": "Парагвай" },
  { "code": "BO", "region": "Өмнөд Америк", "name": "Боливи" },
  { "code": "GY", "region": "Өмнөд Америк", "name": "Гайана" },
  { "code": "SR", "region": "Өмнөд Америк", "name": "Суринам" },
  { "code": "AU", "region": "Австрали", "name": "Австрали" },
  { "code": "NZ", "region": "Австрали", "name": "Шинэ Зеланд" },
  { "code": "FJ", "region": "Австрали", "name": "Фижи" },
  { "code": "PG", "region": "Австрали", "name": "Папуа Шинэ Гвиней" },
  { "code": "NC", "region": "Австрали", "name": "Шинэ Каледони" },
  { "code": "VU", "region": "Австрали", "name": "Вануату" },
  { "code": "SB", "region": "Австрали", "name": "Соломоны арлууд" },
  { "code": "WS", "region": "Австрали", "name": "Самоа" },
  { "code": "TO", "region": "Австрали", "name": "Тонга" },
  { "code": "PF", "region": "Австрали", "name": "Францын Полинез" },
  { "code": "GU", "region": "Австрали", "name": "Гуам" },
  { "code": "SA", "region": "Дундад Зүүн", "name": "Саудын Араб" },
  { "code": "AE", "region": "Дундад Зүүн", "name": "Арабын Нэгдсэн Эмирт Улс" },
  { "code": "QA", "region": "Дундад Зүүн", "name": "Катар" },
  { "code": "OM", "region": "Дундад Зүүн", "name": "Оман" },
  { "code": "BH", "region": "Дундад Зүүн", "name": "Бахрейн" },
  { "code": "KW", "region": "Дундад Зүүн", "name": "Кувейт" },
  { "code": "JO", "region": "Дундад Зүүн", "name": "Йордан" },
  { "code": "LB", "region": "Дундад Зүүн", "name": "Ливан" },
  { "code": "SY", "region": "Дундад Зүүн", "name": "Сири" },
  { "code": "IQ", "region": "Дундад Зүүн", "name": "Ирак" },
  { "code": "IR", "region": "Дундад Зүүн", "name": "Иран" },
  { "code": "YE", "region": "Дундад Зүүн", "name": "Йемен" },
  { "code": "IL", "region": "Дундад Зүүн", "name": "Израиль" },
  { "code": "PS", "region": "Дундад Зүүн", "name": "Палестин" },
  { "code": "ZA", "region": "Африк", "name": "Өмнөд Африк" },
  { "code": "EG", "region": "Африк", "name": "Египет" },
  { "code": "MA", "region": "Африк", "name": "Марокко" },
  { "code": "DZ", "region": "Африк", "name": "Алжир" },
  { "code": "TN", "region": "Африк", "name": "Тунис" },
  { "code": "LY", "region": "Африк", "name": "Ливи" },
  { "code": "SD", "region": "Африк", "name": "Судан" },
  { "code": "SO", "region": "Африк", "name": "Сомали" },
  { "code": "KE", "region": "Африк", "name": "Кени" },
  { "code": "TZ", "region": "Африк", "name": "Танзани" },
  { "code": "UG", "region": "Африк", "name": "Уганда" },
  { "code": "RW", "region": "Африк", "name": "Руанда" },
  { "code": "BI", "region": "Африк", "name": "Бурунди" },
  { "code": "ET", "region": "Африк", "name": "Этиоп" },
  { "code": "ER", "region": "Африк", "name": "Эритрей" },
  { "code": "DJ", "region": "Африк", "name": "Джибути" },
  { "code": "NG", "region": "Африк", "name": "Нигери" },
  { "code": "GH", "region": "Африк", "name": "Гана" },
  { "code": "CI", "region": "Африк", "name": "Кот-д'Ивуар" },
  { "code": "SN", "region": "Африк", "name": "Сенегал" },
  { "code": "ML", "region": "Африк", "name": "Мали" },
  { "code": "GN", "region": "Африк", "name": "Гвиней" },
  { "code": "BJ", "region": "Африк", "name": "Бенин" },
  { "code": "TG", "region": "Африк", "name": "Того" },
  { "code": "CM", "region": "Африк", "name": "Камерун" },
  { "code": "GA", "region": "Африк", "name": "Габон" },
  { "code": "CD", "region": "Африк", "name": "Бүгд Найрамдах Ардчилсан Конго Улс" },
  { "code": "CG", "region": "Африк", "name": "Конго" },
  { "code": "AO", "region": "Африк", "name": "Ангол" },
  { "code": "ZM", "region": "Африк", "name": "Замби" },
  { "code": "ZW", "region": "Африк", "name": "Зимбабве" },
  { "code": "MW", "region": "Африк", "name": "Малави" },
  { "code": "MZ", "region": "Африк", "name": "Мозамбик" },
  { "code": "BW", "region": "Африк", "name": "Ботсвана" },
  { "code": "NA", "region": "Африк", "name": "Намиби" },
  { "code": "LS", "region": "Африк", "name": "Лесото" },
  { "code": "SZ", "region": "Африк", "name": "Эсватини" },
  { "code": "MG", "region": "Африк", "name": "Мадагаскар" },
  { "code": "KM", "region": "Африк", "name": "Коморос" },
  { "code": "MR", "region": "Африк", "name": "Мавритани" },
  { "code": "GM", "region": "Африк", "name": "Гамби" },
  { "code": "GW", "region": "Африк", "name": "Гвиней-Бисау" },
  { "code": "AZ", "region": "Ази", "name": "Азербайжан" },
  { "code": "AL", "region": "Европ", "name": "Албани" },
  { "code": "RE", "region": "Африк", "name": "Реюньон" },
  { "code": "AM", "region": "Ази", "name": "Армен" },
  { "code": "JE", "region": "Европ", "name": "Жерси" },
  { "code": "ME", "region": "Европ", "name": "Монтенегро" },
  { "code": "LU", "region": "Европ", "name": "Люксембург" },
  { "code": "GE", "region": "Ази", "name": "Гүрж" },
  { "code": "IM", "region": "Европ", "name": "Мэн Арал" },
  { "code": "AX", "region": "Европ", "name": "Аланд Арлууд" },
  { "code": "GF", "region": "Өмнөд Америк", "name": "Францын Гвиана" },
  { "code": "MK", "region": "Европ", "name": "Хойд Македон" },
  { "code": "FO", "region": "Европ", "name": "Фарер Арлууд" },
  { "code": "AD", "region": "Европ", "name": "Андорра" },
  { "code": "LI", "region": "Европ", "name": "Лихтенштейн" },
  { "code": "GI", "region": "Европ", "name": "Гибралтар" },
  { "code": "MU", "region": "Африк", "name": "Маврики" },
  { "code": "SC", "region": "Африк", "name": "Сейшел Арлууд" },
  { "code": "TC", "region": "Хойд Америк", "name": "Турк Кайкос" },
  { "code": "GG", "region": "Европ", "name": "Гернси" },
  { "code": "TD", "region": "Африк", "name": "Чад" },
  { "code": "CW", "region": "Хойд Америк", "name": "Кюрасао" },
  { "code": "GP", "region": "Хойд Америк", "name": "Гваделуп" },
  { "code": "NE", "region": "Африк", "name": "Нигер" },
  { "code": "BN", "region": "Ази", "name": "Бруней" },
  { "code": "AI", "region": "Хойд Америк", "name": "Ангилья" },
  { "code": "BM", "region": "Хойд Америк", "name": "Бермуд" },
  { "code": "DM", "region": "Хойд Америк", "name": "Доминик" },
  { "code": "MN", "region": "Ази", "name": "Монгол" },
  { "code": "KY", "region": "Хойд Америк", "name": "Кайман Арлууд" },
  { "code": "BF", "region": "Африк", "name": "Буркина Фасо" },
  { "code": "AG", "region": "Хойд Америк", "name": "Антигуа Барбуда" },
  { "code": "GD", "region": "Хойд Америк", "name": "Гренад" },
  { "code": "LC", "region": "Хойд Америк", "name": "Сент Люси" },
  { "code": "VG", "region": "Хойд Америк", "name": "Британийн Виржин Арлууд" },
  { "code": "KN", "region": "Хойд Америк", "name": "Сент Китс Невис" },
  { "code": "MS", "region": "Хойд Америк", "name": "Монтсеррат" },
  { "code": "SL", "region": "Африк", "name": "Сьерра Леон" },
  { "code": "VC", "region": "Хойд Америк", "name": "Сент Винсент Гренадин" },
  { "code": "CF", "region": "Африк", "name": "Төв Африкийн Бүгд Найрамдах Улс" },
  { "code": "LR", "region": "Африк", "name": "Либери" },
  { "code": "CV", "region": "Африк", "name": "Кабо Верде" },
  { "code": "GL", "region": "Хойд Америк", "name": "Гренланд" },
  { "code": "MC", "region": "Европ", "name": "Монако" },
  {
    "code": "EU-30",
    "region": "Бүс нутгаар",
    "name": "Европ 30 өдөр"
  },
  {
    "code": "EU-7",
    "region": "Бүс нутгаар",
    "name": "Европ 7 өдөр"
  },
  {
    "code": "EU-42",
    "region": "Бүс нутгаар",
    "name": "Европ 42 өдөр"
  },
  {
    "code": "EU-43",
    "region": "Бүс нутгаар",
    "name": "Европ 43 өдөр"
  },
  {
    "code": "CB-24",
    "region": "Бүс нутгаар",
    "name": "Дэлхий даяар 24 өдөр"
  },
  {
    "code": "CB-25",
    "region": "Бүс нутгаар",
    "name": "Дэлхий даяар 25 өдөр"
  },
  {
    "code": "SGMYTH-3",
    "region": "Бүс нутгаар",
    "name": "Сингапур, Малайз, Тайланд 3 өдөр"
  },
  {
    "code": "SGMY-2",
    "region": "Бүс нутгаар",
    "name": "Сингапур, Малайз 2 өдөр"
  },
  {
    "code": "BI-2",
    "region": "Бүс нутгаар",
    "name": "Британи, Ирланд 2 өдөр"
  },
  {
    "code": "AUNZ-2",
    "region": "Бүс нутгаар",
    "name": "Австрали, Шинэ Зеланд 2 өдөр"
  },
  {
    "code": "USCA-2",
    "region": "Бүс нутгаар",
    "name": "АНУ, Канад 2 өдөр"
  },
  {
    "code": "NA-3",
    "region": "Бүс нутгаар",
    "name": "Хойд Америк 3 өдөр"
  },
  {
    "code": "CNJPKR-3",
    "region": "Бүс нутгаар",
    "name": "Хятад, Япон, Солонгос 3 өдөр"
  },
  {
    "code": "JPKR-2",
    "region": "Бүс нутгаар",
    "name": "Япон, Солонгос 2 өдөр"
  },
  {
    "code": "SGMYVNTHID-5",
    "region": "Бүс нутгаар",
    "name": "Сингапур, Малайз, Вьетнам, Тайланд, Индонез 5 өдөр"
  },
  {
    "code": "ME-6",
    "region": "Бүс нутгаар",
    "name": "Ойрх Дорнод 6 өдөр"
  },
  {
    "code": "AS-21",
    "region": "Бүс нутгаар",
    "name": "Ази 21 өдөр"
  },
  {
    "code": "CA-4",
    "region": "Бүс нутгаар",
    "name": "Канад 4 өдөр"
  },
  {
    "code": "CNHK-2",
    "region": "Бүс нутгаар",
    "name": "Хятад, Хонг Конг 2 өдөр"
  },
  {
    "code": "AUKUS-3",
    "region": "Бүс нутгаар",
    "name": "Австрали, Их Британи, АНУ 3 өдөр"
  },
  {
    "code": "AS-20",
    "region": "Бүс нутгаар",
    "name": "Ази 20 өдөр"
  },
  {
    "code": "SAAEQAKWOMBH-6",
    "region": "Бүс нутгаар",
    "name": "Саудын Араб, АНЭУ, Катар, Кувейт, Оман, Бахрейн 6 өдөр"
  },
  {
    "code": "GL-120",
    "region": "Бүс нутгаар",
    "name": "Дэлхий даяар 120 өдөр"
  },
  {
    "code": "SA-18",
    "region": "Бүс нутгаар",
    "name": "Өмнөд Америк 18 өдөр"
  },
  {
    "code": "AF-29",
    "region": "Бүс нутгаар",
    "name": "Африк 29 өдөр"
  },
  {
    "code": "ME-13",
    "region": "Бүс нутгаар",
    "name": "Ойрх Дорнод 13 өдөр"
  },
  {
    "code": "ME-12",
    "region": "Бүс нутгаар",
    "name": "Ойрх Дорнод 12 өдөр"
  },
  {
    "code": "GL-139",
    "region": "Бүс нутгаар",
    "name": "Дэлхий даяар 139 өдөр"
  }
]